{"1": {"circuits": {"1": {"activated": true, "time": 1}, "2": {"activated": true, "time": 2}, "3": {"activated": true, "time": 1}, "4": {"activated": true, "time": 3}, "5": {"activated": false, "time": 0}, "6": {"activated": true, "time": 1}, "7": {"activated": false, "time": 0}, "8": {"activated": false, "time": 2}, "9": {"activated": false, "time": 0}, "10": {"activated": false, "time": 0}, "11": {"activated": true, "time": 0}, "12": {"activated": false, "time": 0}}, "days": {"D": false, "J": false, "L": false, "M": false, "S": true, "V": false, "X": true}, "selected": false, "starts": {"1": {"activated": true, "hour": "10:00"}, "2": {"activated": true, "hour": "09:35"}, "3": {"activated": false, "hour": "09:00"}}}, "2": {"circuits": {"1": {"activated": false, "time": 0}, "2": {"activated": false, "time": 0}, "3": {"activated": true, "time": 5}, "4": {"activated": true, "time": 2}, "5": {"activated": false, "time": 0}, "6": {"activated": false, "time": 0}, "7": {"activated": false, "time": 0}, "8": {"activated": false, "time": 0}, "9": {"activated": true, "time": 0}, "10": {"activated": false, "time": 0}, "11": {"activated": false, "time": 0}, "12": {"activated": false, "time": 0}}, "days": {"D": true, "J": true, "L": true, "M": false, "S": false, "V": false, "X": false}, "selected": true, "starts": {"1": {"activated": true, "hour": "10:29"}, "2": {"activated": false, "hour": "09:00"}, "3": {"activated": false, "hour": "00:00"}}}, "3": {"circuits": {"1": {"activated": true, "time": 1}, "2": {"activated": false, "time": 0}, "3": {"activated": false, "time": 0}, "4": {"activated": false, "time": 0}, "5": {"activated": true, "time": 2}, "6": {"activated": false, "time": 0}, "7": {"activated": false, "time": 0}, "8": {"activated": false, "time": 0}, "9": {"activated": false, "time": 0}, "10": {"activated": false, "time": 0}, "11": {"activated": false, "time": 0}, "12": {"activated": false, "time": 0}}, "days": {"D": false, "J": false, "L": false, "M": true, "S": true, "V": false, "X": false}, "selected": true, "starts": {"1": {"activated": true, "hour": "16:27"}, "2": {"activated": true, "hour": "20:16"}, "3": {"activated": false, "hour": "00:00"}}}}